{"title":"Полигон","markdown":{"headingText":"Полигон","containsRefs":false,"markdown":"\n**Провинция Ганьсу, Китай. Испытательная база «Гелиос-Земля». 2028.**\n\nВертолёт опустился на бетонную площадку, подняв облако жёлтой пыли. Павел спрыгнул на землю, придерживая сумку с документами, и сразу почувствовал ветер --- сухой, с привкусом песка, который царапал горло и забивался в волосы. Вокруг простиралась пустыня --- бесконечная, серо-жёлтая, потрескавшаяся земля до самого горизонта, где небо сливалось с барханами в одну размытую линию. Это было не похоже ни на что, что он видел раньше: ни на подмосковные леса, ни на казахстанские степи, через которые они летели три часа. Это было похоже на Меркурий --- насколько Земля вообще может быть похожа на другую планету.\n\nБаза раскинулась у подножия невысокого хребта: модульные корпуса цвета песка, три огромных ангара с раздвижными крышами, антенные фермы, опутанные кабелями, и вышка управления с панорамным остеклением. На флагштоке у входа --- три флага: российский триколор, красный флаг КНР и оранжево-бело-зелёный флаг Индии, все потрёпанные ветром до белёсости. Надписи на воротах шли в три ряда --- кириллица сверху, иероглифы посередине, деванагари снизу: «Испытательная база «Гелиос-Земля». Объединённый проект».\n\nПавел остановился, глядя на ангары. Где-то там, за стальными воротами, стояли роботы --- те самые, которых он видел только на чертежах и в симуляциях. Пауки, Крабы, Кентавры, Кроты. Пятьдесят шесть машин, которые через несколько лет должны построить первый завод на Луне. А ещё через десять --- превратить Меркурий в энергетическое сердце цивилизации. Если всё пойдёт по плану. Если ничего не сломается. Если он не облажается.\n\nВалерий Петрович должен был быть здесь. Он ждал этого дня три года --- увидеть, как первые роботы проекта выезжают на испытания. Но здоровье подвело: сердце, которое годами игнорировало предупреждения врачей, наконец потребовало внимания.\n\nК нему подошёл Ли Вэй --- координатор с китайской стороны, с которым Павел встречался год назад в Шэньчжэне, когда ездил по заводам вместе с Валерием Петровичем. Короткие седеющие волосы, знакомое спокойное лицо человека, привыкшего решать проблемы, а не создавать их. Только комбинезон сменился с офисного костюма на серую рабочую форму. Они пожали друг другу руки --- крепкая хватка, которую Павел помнил.\n--- Добро пожаловать на базу. --- Ли Вэй заметил, что Павел один. --- Валерий Петрович не приехал?\n--- Здоровье. Сердце. Врачи запретили перелёты.\n--- Передайте ему от меня: его чертежи висят в каждом ангаре здесь. --- Ли Вэй склонил голову с пониманием, потом указал в сторону ангаров. --- Пойдёмте, покажу обстановку. У нас много работы и мало времени.\n\nПо дороге к ангару к ним присоединилась женщина лет тридцати, в синем комбинезоне с логотипом проекта --- худощавая, с короткими тёмными волосами, собранными в практичный хвост, и уставшими глазами человека, который только что закончил ночную смену. Павел узнал её сразу.\n--- Вайшали. --- Он протянул руку. --- Не ожидал увидеть вас здесь.\n--- Нейросети требуют полевых испытаний, --- ответила она с лёгким акцентом, пожимая руку. --- Бангалор хорош для симуляций, но здесь --- реальные роботы, реальная пыль, реальные отказы. Основная команда осталась в Индии, координируемся по видеосвязи каждый день. Плюс местные специалисты из Шэньчжэня --- у китайцев огромный опыт в обучении нейросетей, без них не справились бы.\n--- Как работает роевой интеллект? --- спросил Павел.\n--- Лучше, чем ожидалось. Хуже, чем хотелось бы. --- Она достала планшет и показала график. --- Координация на уровне девяноста двух процентов, но есть краевые случаи --- когда три Краба пытаются взять один контейнер одновременно. Приоритеты конфликтуют. Дообучаем модель.\n\n--- Она работает с Виктором, --- подтвердил Ли Вэй. --- Железо и софт. Два ведущих инженера. Виктор отвечает за механику и телеметрию, Вайшали --- за нейросети. Разные системы, но работают в паре.\n\nОни шли по центральной аллее базы --- бетонной дорожке между модулями, по которой то и дело проезжали грузовики с контейнерами. Ли Вэй говорил ровно, без эмоций, как будто зачитывал отчёт:\n\n--- Первая партия оборудования прибыла в прошлом месяце. Логистика --- кошмар. Порт Тяньцзинь, железная дорога до Ланьчжоу, потом грузовики через горы --- четыреста километров серпантина по перевалу. Три контейнера повредили в пути, пришлось заказывать повторно.\n\n--- Критичные компоненты?\n\n--- К счастью, нет. Рамы для стапелей, расходные материалы. Но это показывает масштаб проблемы. Когда начнём возить модули для реальной миссии --- а это двадцать тонн каждый --- будет сложнее.\n\nПавел кивнул. Он видел маршрут на картах: Россия, Казахстан, Китай. Тысячи километров границ, таможен, перегрузок. И это только земная часть. До Луны оставались годы. До Меркурия --- тоже.\n\nОни остановились у склада с открытыми воротами. Внутри --- штабеля ящиков с маркировкой на разных языках. Павел заметил надписи: «Shenzhen Precision Drives», «Bangalore Sensors Ltd.», «НПО Энергомаш». И ни одной японской.\n\n--- Где приводы от Nidec? --- спросил он. --- По спецификации должны были прийти три недели назад.\nЛи Вэй не сразу ответил --- взгляд его задержался на ящиках. --- Токио задерживает. Официально --- «логистические сложности». Неофициально --- давление из Вашингтона. Nidec --- акционерное общество, половина акций на американских биржах. Им намекнули, что сотрудничество с «Гелиосом» может создать проблемы с лицензиями. Извиняются, обещают решить, но сроки растут.\n\nКулаки сжались сами собой. Павел вспомнил аналитическую записку, которую читал перед вылетом: «Вашингтонская стена. Контроль узких мест в цепочках поставок». Это была не абстракция --- это было здесь, в ящиках с надписями «Made in Shenzhen» вместо «Made in Yokohama».\n\n--- Что используем вместо?\n--- Китайские аналоги. --- Ли Вэй указал на ящики слева. --- Шэньчжэньский завод. Грубее, люфт выше --- три десятых градуса против одной десятой у японцев. Но работают. Мы уже установили их на три Кентавра для тестов.\n--- Для Луны три десятых --- критично, --- сказал Павел. --- Для Меркурия --- катастрофа.\n--- Понимаю. Поэтому вас и ждали. Нужно решение --- техническое, не политическое.\n\nОн перевёл взгляд на ящики. Где-то в этих металлических коробках лежала судьба проекта --- и ему предстояло собрать её по частям.\n\n\nАнгар номер один --- «Зоопарк», как его называли на базе --- занимал площадь футбольного поля. Павел остановился у входа и замер.\n\nПятьдесят шесть машин стояли в рядах --- разных форм и размеров, от шестиногих Пауков до громадин-Крабов на сетчатых колёсах. Белая керамика, золотистые гофры на суставах, острые когти из тёмного металла. Кентавры в центре --- полуроботы-полуроверы с руками-манипуляторами. Кроты в дальнем углу --- приземистые, злые, с бульдозерными отвалами. Павел видел их на чертежах сотни раз, но здесь, в металле --- они казались живыми. Спящей армией, ждущей приказа.\n\nВалерий Петрович должен был это видеть.\n\n--- Красивые, --- сказал Павел, не сразу понимая, что произнёс это вслух.\n--- Красота --- это функция, --- ответил голос сзади.\n\nПавел обернулся. Виктор стоял с планшетом в руках --- измождённый вид, графики телеметрии на экране. Тот же вид, что и в Москве месяц назад, только загар от пустынного солнца.\n\n--- Три дня как начали тесты, --- сказал он без приветствий. --- Есть проблемы.\n\n--- Какие?\n\nВиктор повернул планшет экраном к нему. На графике --- две линии: синяя и красная. Синяя --- японские приводы, гладкая, как шёлк. Красная --- китайские, с мелкими зубцами, похожими на кардиограмму. --- Люфт, --- объяснил он. --- 0,3° на холостом ходу, до 0,5° под нагрузкой. Кентавры с такими приводами не могут выдержать допуски на сборку. Болт, который нужно закрутить с моментом двадцать ньютон-метров, получает либо пятнадцать, либо двадцать пять. На Луне развалится через месяц, когда термоциклы разболтают соединения. На Меркурии --- через три дня.\n\nПавел повернулся к Кентаврам --- стройным, элегантным машинам с руками, способными собирать микросхемы, --- и представил их на Меркурии, под палящим солнцем, с люфтом в полградуса. --- Решение есть?\n--- Два варианта. Первый --- ждать японцев, месяц, два, полгода. Второй --- компенсировать программно.\n\nВайшали, стоявшая рядом с графиками, подняла голову от планшета и подошла ближе, показывая экран Павелу. --- У нас есть датчики силы, обратная связь работает в реальном времени. Нужна нейросеть, которая будет обучаться на каждом затянутом болте. Теоретически --- возможно. Практически --- никто ещё не пробовал на таком железе. Не уверена, что успеем за неделю, но нам нужны данные --- много данных. Каждый болт, каждая ошибка --- это обучающая выборка.\n--- Три Кентавра с китайскими приводами уже работают, --- согласился Виктор. --- Логи идут каждую секунду. За сутки наберём тысячи примеров.\n--- Этого мало для обучения с нуля, --- возразила Вайшали. --- Но достаточно для дообучения базовой модели. У нас есть симуляции из Бангалора --- сто тысяч виртуальных болтов. Перенесём веса, донастроим на реальном железе.\n\nПавел наблюдал за ними --- два специалиста, два языка, железо и софт, но они говорили об одном и том же. Это было хорошим знаком.\n\n--- Что нужно от меня? --- спросил он.\n\n--- Приоритет для моей команды в Бангалоре --- чтобы не дёргали на другие задачи, --- ответила Вайшали. --- И вычислительные мощности: обучение модели требует GPU-кластер. --- Она взглянула на Виктора. --- Сколько нам нужно времени?\n\n--- Пять дней на разработку, ещё два на валидацию. К субботе будем готовы.\n\n--- Ресурсы будут, --- сказал Павел. --- Начинайте.\n\n\nСледующие дни слились в один непрерывный поток. Павел вставал в шесть, ложился в полночь, а между этими точками --- совещания, тесты, отчёты, звонки в Москву и Пекин. Пауки на скале, Крабы с грузами, Кроты в песке --- всё работало, скрипело, гудело. Пыль забивала фильтры и скрипела на зубах.\n\nНо главное --- Кентавры. Виктор и Вайшали работали по четырнадцать часов в сутки, и их модули стояли рядом --- два тесных помещения, соединённых коротким коридором, где постоянно горел свет. Павел заходил к ним ночью и видел одну и ту же картину: Виктор за терминалом с графиками телеметрии, Вайшали --- с логами обучения нейросети, и между ними --- непрерывный диалог через открытую дверь.\n\n--- Люфт на пятом болте --- ноль четыре градуса, --- докладывал Виктор.\n\n--- Вижу. Модель предсказала ноль три. Корректирую веса, --- отвечала Вайшали, не отрывая глаз от экрана.\n\n--- Момент затяжки --- двадцать два ньютон-метра вместо двадцати. Переучилась?\n\n--- Нет. Компенсирует предыдущую ошибку. К десятому болту выйдет в ноль.\n\nПавел слушал их перекличку --- технический жаргон, цифры, короткие фразы без лишних слов --- и понимал: они работают как одна система. Виктор даёт данные, Вайшали обучает модель, модель улучшается, Виктор тестирует снова. Замкнутый цикл, который с каждым часом становился точнее.\n\nНа третий день --- первый успех. Кентавр с китайскими приводами собрал тестовый модуль с точностью 0,15° --- вдвое лучше, чем без компенсации. На четвёртый --- 0,12°. На пятый --- 0,10°, почти на уровне японских приводов.\n\n--- Как? --- спросил Павел, глядя на графики.\n\nВайшали и Виктор стояли рядом, оба помятые после бессонной ночи, с кофеиновым тремором в руках. Вайшали ответила первой:\n\n--- Нейросеть обучается на каждом затянутом болте. Входные данные --- датчики силы, угол поворота, скорость привода. Выход --- коррекция момента. После ста болтов модель понимает привод лучше, чем спецификация от производителя.\n\n--- Это работает только на этом конкретном приводе? --- спросил Павел.\n\nВиктор покачал головой. --- Нет. Модель обобщается. Новый привод --- сто болтов на калибровку, потом работает. Мы можем ставить любые приводы, хоть индийские, хоть иранские.\n\n--- Софт компенсирует, --- добавила Вайшали с усталой улыбкой. --- Вашингтон хотел контролировать железо. Но они забыли про математику.\n\nОн окинул их взглядом --- двух измотанных специалистов, которые только что обошли политическую блокаду через инженерию --- и кивнул. Этого было достаточно.\n\n\nВторой ангар --- «Кокон» --- был закрыт для посторонних. Внутри, под герметичным куполом с пониженным давлением, располагался макет завода «Точка Ноль» --- того самого, который через несколько лет должен заработать на Меркурии. Павел вошёл через шлюз, надев комбинезон и маску, и почувствовал, как уши закладывает от перепада давления --- внутри поддерживали десятую часть атмосферы, как на настоящем заводе.\n\nПод ногами --- не бетон, а серо-коричневый порошок, хрустящий под подошвами. Симулянт --- двадцать тысяч тонн искусственного реголита, синтезированного по меркурианскому составу: оксиды железа, алюминия, кремния. Его везли сюда полгода --- железной дорогой из Ланьчжоу, грузовиками через перевал. Кроты рыли в нём траншеи, солнечные печи плавили его в слитки. Настоящий Меркурий был в ста миллионах километров, но здесь всё было максимально близко к реальности --- кроме гравитации.\n\nПолумрак. Оранжевое свечение пульсирует в центре --- расплавленный металл течёт из солнечной печи, концентрированный свет бьёт через кварцевые окна, и сталь превращается в жидкую реку, стекающую по гравитационно-поточной линии вниз: в форму, в слиток, в пруток, в проволоку. Визг, скрежет, снопы искр. В нос бьёт запах окалины и чего-то электрического --- озон от дуговых сварочных головок. Павел остановился, заворожённый: это было похоже на кровеносную систему, на сердце, качающее сталь вместо крови. Всё здесь двигалось сверху вниз --- расплав тяжелее шлака, чистый металл тяжелее примесей, готовые детали опускаются на нижний уровень. Гравитация как сортировщик. Здесь рождалось будущее --- деталь за деталью.\n\nТри станции WAAM --- аддитивной дуговой сварки --- работали одновременно, наращивая металл слой за слоем по цифровой модели. На одной из них рос корпус Паука --- тонкие рёбра жёсткости, гнёзда для сервоприводов, пустоты для проводки. Всё создавалось за один проход, без болтов, без сварных швов --- монолитная деталь прямо из проволоки.\n\nНа стапеле рядом лежала половина корпуса Крота --- ещё тёплая, с характерными ребристыми полосами от послойного наращивания. Павел коснулся металла. Шершавый, настоящий. Не чертёж, не симуляция. Кусок будущего, материализовавшийся в китайской пустыне.\n\nРуководитель производственной группы из Харбина --- маленькая женщина в огромных очках, с усталым лицом человека, который провёл здесь слишком много ночных смен --- заметила его интерес и отошла от терминала, где двое её инженеров отслеживали параметры плавки.\n\n--- Вся линия работает на пяти мегаваттах, --- сказала она, опережая вопрос. --- Печи, WAAM-станции, CNC-фрезеры для финишной обработки. На Меркурии энергия будет бесплатная, здесь платим за каждый киловатт, но точность процессов та же. --- Она обвела рукой купол. --- Пока тестируем при десятой атмосферы. Следующий этап --- вакуумные камеры для критичных узлов. Потом полный цикл при лунном давлении. К Меркурию подойдём постепенно. --- Она помолчала, взгляд скользнул к одной из сварочных головок. --- Проблема --- вот эта горелка. Немецкая. Под экспортным контролем. Единственная, которая даёт нужную точность на титановых сплавах. Если сломается --- останемся без производства титановых узлов на неопределённый срок.\n\nГорелка притягивала внимание --- маленький кусок металла и оптики, от которого зависела вся программа. Одна деталь. Один поставщик. Одна точка отказа.\n\n--- Моя группа в Шэньчжэне работает над своей версией, --- добавила она тише. --- Двенадцать человек. Полгода до прототипа. Год --- до серийного образца. Но пока... --- Она пожала плечами. --- Значит, не сломаем.\n\nПавел узнал в этих словах интонацию Валерия Петровича --- упрямство людей, которые делают невозможное, потому что выбора нет.\n\n\nНа шестой день --- полный цикл испытаний. Все системы работали одновременно: Пауки на скале, Крабы с грузами, Кентавры на сборке, Кроты на добыче, «Кокон» на производстве. Центр управления гудел от голосов операторов, экраны пестрели телеметрией, графики ползли вверх и вниз, как кардиограммы живых существ. Павел стоял за спиной Виктора, наблюдая за данными. Всё шло по плану --- почти.\n\n--- Микроотклонения, --- сказал Виктор, не поднимая глаз от монитора. --- Третий контур охлаждения. Температура.\n\nПавел вгляделся в график --- аккуратные зубцы, едва заметные, как тихие вдохи в записи дыхания. Ноль семь градуса. Три раза за сутки. Синхронизированы с калибровкой. --- Это шум?\n--- Шум --- это когда ты знаешь источник, --- ответил Виктор. --- А когда не знаешь --- это событие.\n\nЭтот тон был знаком. Так говорят о вещах, которые кажутся мелочью, но могут убить проект. --- Что предлагаешь?\n--- Остановить цикл. Перегнать тест отказоустойчивости. Найти источник. Это сутки, минимум.\n\nПавел промолчал. Сутки --- это ещё один день отставания от графика. Виктор ждал. Павел вспомнил звонок из Москвы: «Американцы запустили SunGrid. Нужно ускориться». --- Запускаем по графику, --- сказал он наконец. --- Но журнал --- на моём столе каждое утро. И если зубцы повторятся --- остановимся.\n--- Я записал, --- отозвался Виктор.\n\nВечером Виктор принёс распечатку. Лист бумаги --- старомодный жест в эпоху цифровых документов, но Виктор понимал силу физического присутствия вещей. Внизу --- аккуратный почерк: «Повторение отклонения на 0,6°C. Режим --- калибровка. Модуль --- шлюз №2. Запрос на дополнительную проверку --- отклонён».\n\nПавел взял лист и долго смотрел на него, словно буквы могли рассказать больше, чем говорили. Ноль шесть градуса. Три раза за сутки. Синхронизация с калибровкой. Это могла быть ошибка датчика. Помеха в цепи. Программный глюк. А могла быть утечка в шлюзе --- микротрещина, невидимая глазу, которая на Меркурии превратится в катастрофу за секунды.\n\nОн знал, что должен сделать. Остановить испытания. Провести полную диагностику. Найти причину. Так требовала инженерная этика. Так говорил здравый смысл.\n\nНо он также знал другое. Звонок из Москвы: «Американцы торопятся». Давление от Ли Вэя: «Пекин задаёт вопросы». Графики на стене, где каждый день задержки --- красная линия, уходящая вниз. Инвесторы, которые уже нервничают. Индия, которая «пересмотрит участие». Тысячи людей, которые работают на этот проект, и все они ждут результатов.\n\nНоль шесть градуса.\n\nВалерий Петрович бы остановил. Он всегда останавливался, когда сомневался. «Лучше месяц задержки, чем год исправлений». Но это было другое время, другой мир --- государственные программы, не консорциумы с квартальными отчётами.\n\nЗапрос на дополнительную проверку --- отклонён. Отклонён им. Его решение. Его ответственность.\n\nПавел поставил ручку на бумагу, чтобы завизировать. Пальцы не двигались.\n\n--- Я подпишу, --- сказал он вслух, то ли Виктору, то ли себе.\n\nНо не подписал. Положил лист на стол, придавив его углом монитора, и уставился в тёмное окно. Завтра. Он решит завтра. Когда будут новые данные. Когда станет яснее.\n\n\nВечером терминал мигнул входящим вызовом.\n\nНа экране появился логотип частной космической компании --- той самой, чьи ракеты садились на хвост и летали к МКС чаще других. Павел принял вызов.\n\nЛицо на экране было знакомо по новостям: худое, с глубоко посаженными глазами, техасский акцент. За спиной --- хаос рабочего кабинета, чертежи, модели ракет.\n\n--- Досточкин? У меня десять минут. --- Голос был хриплый, без церемоний. --- Я слежу за вашим проектом. Год назад появились патентные заявки --- сплавы, алгоритмы роя, WAAM в вакууме. Вы не исследуете. Вы строите. И я хочу участвовать.\n\nПавел не ожидал такой прямоты. --- Участвовать как?\n\n--- Мои ракеты возят двести тонн на орбиту. Это больше любого вашего носителя. Коммерческий контракт, частная компания, без государственных печатей.\n\n--- Вы же понимаете, что это невозможно, --- сказал Павел. --- ITAR, CFIUS, экспортный контроль. Ваши законы не позволят.\n\nАмериканец откинулся в кресле. --- Знаю. Год пытался получить разрешение. Сенаторы, Пентагон, Белый дом. Везде одно и то же: критические технологии, потенциальный противник. --- Он пожал плечами. --- Не вышло. Пока.\n\n--- Тогда зачем звонок?\n\n--- Чтобы вы знали: когда проект заработает, правила изменятся. Деньги меняют правила. И тогда я приду снова.\n\n--- А если не изменятся?\n\nАмериканец усмехнулся. --- Тогда построю свои зеркала сам. На Марсе. Без разрешения Конгресса. --- Он бросил взгляд куда-то за камеру. --- Мне пора. Удачи с испытаниями.\n\nЭкран погас. Павел ещё несколько минут смотрел на тёмный монитор, думая о том, что союзники бывают в самых неожиданных местах.\n\n\nНа следующий день --- созвон с Москвой. Павел сидел в маленьком кабинете административного модуля, на экране --- три окна: Валерий Петрович из дома, Серёжа из офиса, Ли Вэй из соседнего корпуса.\n\n--- Давление растёт, --- начал Павел. --- Из Пекина, из Москвы. Американцы запустили SunGrid. Нам нужно ускориться --- сократить фазу испытаний, перейти к Луне раньше срока.\n\nСерёжа покачал головой.\n\n--- Это самоубийство. Мы не закончили калибровку, не нашли источник термических отклонений. Потеряем первую партию --- проект отбросит на пять лет.\n\n--- Мы не можем ждать вечно, --- возразил Павел. --- Каждый месяц задержки --- это потеря политической поддержки.\n\n--- Лучше потерять поддержку, чем потерять миссию, --- сказал Валерий Петрович. --- Месяц задержки --- не год исправлений.\n\n--- Из Пекина давят, --- добавил Ли Вэй. --- Но я согласен с Серёжей. Если первая партия провалится --- проект закроют. Не отложат. Закроют.\n\nПавел помолчал. Четыре окна на экране, три голоса против. Он знал, что они правы. Знал с самого начала --- просто не хотел признавать.\n\n--- Хорошо. Я подумаю.\n\n\nВечер. Павел стоял на крыше административного модуля --- плоской площадке с антеннами и солнечными панелями --- и смотрел на небо. Звёзды здесь были яркие, как нигде на Земле: пустыня, сухой воздух, отсутствие светового загрязнения. Млечный Путь разливался от горизонта до горизонта, и где-то там, среди миллиардов огней, была цель --- планета размером с Луну, опалённая солнцем, ждущая их.\n\nШаги за спиной --- два человека поднялись по лестнице. Виктор держал три кружки, Вайшали --- термос. --- Чай. Зелёный. Ли Вэй угостил, --- сказал Виктор, протягивая кружку.\n\nПавел взял её --- горячий фарфор обжёг пальцы. Вайшали налила чай из термоса, и горьковатый аромат напомнил о чём-то давно забытом. --- Нашли источник зубцов?\n--- Нет ещё, --- ответил Виктор. --- Но сузили поиск. Скорее всего --- калибровочный модуль в шлюзе.\n--- Это может быть и софт, --- добавила Вайшали. --- Аномалия коррелирует с обновлением прошивки. Я проверяю логи.\n--- Меня беспокоит, что мы продолжаем, не разобравшись, --- сказал Виктор.\n\nПавел молча качнул головой, но ничего не сказал. Он думал о графике, о давлении из Москвы и Пекина, о том, что времени нет. Они стояли втроём, глядя на звёзды. Ветер нёс запах песка и машинного масла.\n\n--- Почему вы здесь? --- спросил он вдруг. --- В пустыне, в тысячах километров от дома. Почему именно этот проект?\n\nВиктор не сразу ответил. --- Потому что это --- настоящее. Не бумажки, не совещания. Здесь делают то, о чём я мечтал в институте. --- Он отхлебнул чай. --- Отец всю жизнь работал над этим проектом. Теперь моя очередь. Я вырос с мыслью, что космос --- это то, ради чего стоит жить.\n\nВайшали задумалась, глядя на звёзды.\n\n--- У меня --- проще. --- Она сделала глоток чая. --- Семья инженеров, Бангалор. В одиннадцать написала первую программу --- сортировка пузырьком. Глупость, но я до сих пор помню, как числа выстроились в правильном порядке. --- Она выдержала паузу. --- Google предлагал втрое больше. Рекомендательные алгоритмы для видео --- оптимизировать время просмотра, увеличивать вовлечённость. Хорошая работа, стабильная. Но это значило делать людей зависимыми от экранов. Использовать математику, чтобы украсть их время. Я не смогла. А здесь --- тысяча роботов на другой планете, учащихся работать вместе. Сложнейшая задача координации, которую никто раньше не решал. Это невозможно. Поэтому --- интересно. И... правильно.\n\nПавел слушал их --- два разных ответа, два разных пути --- и понимал, что проект держится не на технологиях. Он держится на людях, для которых невозможное --- единственная причина вставать по утрам.\n\n--- Вы боитесь? --- спросил Виктор.\n--- Боюсь, когда не знаю, что делать. Сейчас знаю. Просто сложно.\n--- А когда не знаете?\n--- Тогда страшно. --- Павел отхлебнул чай. --- Отец говорил: страх --- это компас. Он показывает, где опасность. Не надо его игнорировать. Надо слушать.\n\nВайшали посмотрела на него внимательно, и Павел понял, что разговор свернул к тому, чего он боялся. --- Вы слушали нас сегодня, --- сказала она тихо. --- Про зубцы в телеметрии. Про аномалии в прошивке. Что решили?\n\n--- Давайте разбираться, --- сказал Павел. --- Завтра с утра.\n\nТри дня диагностики. Источник нашли: окислившийся контакт в калибровочном модуле, микроскопическая коррозия от песчаной пыли. Заменили за час. Зубцы исчезли.\n\n--- Всё? --- спросил Павел.\n\n--- Технически --- да. --- Виктор закрыл журнал. --- Но паттерн был слишком регулярный для случайного окисления.\n\nПавел кивнул. Ему хотелось верить, что проблема решена.\n\nСледующие месяцы --- вакуумные камеры. Условия, близкие к лунным: разрежённая атмосфера, перепады температур, лунная пыль --- абразивная, въедливая, хуже земной. Проблемы возникали постоянно: перегрев приводов, сбои связи, ложные срабатывания датчиков. Каждую неделю --- новый баг, новая доработка, новый цикл тестов. Виктор вёл журнал отказов, Вайшали переписывала код, харбинские инженеры меняли сплавы и покрытия.\n\nК концу года роботы работали в вакууме так же надёжно, как на открытом воздухе. Павел смотрел на графики отказов --- кривая шла вниз, асимптотически приближаясь к нулю. Технология работала. Но впереди --- годы: тесты на радиационную стойкость, интеграция всех систем в единый комплекс, просчёт траекторий доставки, логистика развёртывания на лунной поверхности. Как скомпоновать груз, чтобы роботы могли распаковаться сами. Как синхронизировать сотни машин с задержкой связи в полторы секунды. Как не потерять всё из-за одной ошибки в первые минуты. Работы хватит надолго.\n","srcMarkdownNoYaml":""},"formats":{"html":{"identifier":{"display-name":"HTML","target-format":"html","base-format":"html"},"execute":{"fig-width":7,"fig-height":5,"fig-format":"retina","fig-dpi":96,"df-print":"default","error":false,"eval":true,"cache":null,"freeze":false,"echo":true,"output":true,"warning":true,"include":true,"keep-md":false,"keep-ipynb":false,"ipynb":null,"enabled":null,"daemon":null,"daemon-restart":false,"debug":false,"ipynb-filters":[],"ipynb-shell-interactivity":null,"plotly-connected":true,"engine":"markdown"},"render":{"keep-tex":false,"keep-typ":false,"keep-source":false,"keep-hidden":false,"prefer-html":false,"output-divs":true,"output-ext":"html","fig-align":"default","fig-pos":null,"fig-env":null,"code-fold":true,"code-overflow":"scroll","code-link":false,"code-line-numbers":false,"code-tools":false,"tbl-colwidths":"auto","merge-includes":true,"inline-includes":false,"preserve-yaml":false,"latex-auto-mk":true,"latex-auto-install":true,"latex-clean":true,"latex-min-runs":1,"latex-max-runs":10,"latex-makeindex":"makeindex","latex-makeindex-opts":[],"latex-tlmgr-opts":[],"latex-input-paths":[],"latex-output-dir":null,"link-external-icon":false,"link-external-newwindow":false,"self-contained-math":false,"format-resources":[],"notebook-links":true},"pandoc":{"standalone":true,"wrap":"none","default-image-extension":"png","to":"html","toc":true,"toc-depth":3,"include-in-header":{"text":"<style>\n.content { max-width: 900px; }\np { text-indent: 1.5em; margin-top: 0.3em; margin-bottom: 0.3em; text-align: justify; }\nh1 + p, h2 + p, h3 + p, h4 + p { text-indent: 0; }\np:has(img), .quarto-figure, .figure { text-indent: 0; }\np:has(> strong:first-child) { text-indent: 0; }\np:has(> em:first-child) { text-indent: 0; }\n</style>\n"},"output-file":"09-poligon.html"},"language":{"toc-title-document":"Table of contents","toc-title-website":"On this page","related-formats-title":"Other Formats","related-notebooks-title":"Notebooks","source-notebooks-prefix":"Source","other-links-title":"Other Links","code-links-title":"Code Links","launch-dev-container-title":"Launch Dev Container","launch-binder-title":"Launch Binder","article-notebook-label":"Article Notebook","notebook-preview-download":"Download Notebook","notebook-preview-download-src":"Download Source","notebook-preview-back":"Back to Article","manuscript-meca-bundle":"MECA Bundle","section-title-abstract":"Abstract","section-title-appendices":"Appendices","section-title-footnotes":"Footnotes","section-title-references":"References","section-title-reuse":"Reuse","section-title-copyright":"Copyright","section-title-citation":"Citation","appendix-attribution-cite-as":"For attribution, please cite this work as:","appendix-attribution-bibtex":"BibTeX citation:","appendix-view-license":"View License","title-block-author-single":"Author","title-block-author-plural":"Authors","title-block-affiliation-single":"Affiliation","title-block-affiliation-plural":"Affiliations","title-block-published":"Published","title-block-modified":"Modified","title-block-keywords":"Keywords","callout-tip-title":"Tip","callout-note-title":"Note","callout-warning-title":"Warning","callout-important-title":"Important","callout-caution-title":"Caution","code-summary":"Code","code-tools-menu-caption":"Code","code-tools-show-all-code":"Show All Code","code-tools-hide-all-code":"Hide All Code","code-tools-view-source":"View Source","code-tools-source-code":"Source Code","tools-share":"Share","tools-download":"Download","code-line":"Line","code-lines":"Lines","copy-button-tooltip":"Copy to Clipboard","copy-button-tooltip-success":"Copied!","repo-action-links-edit":"Edit this page","repo-action-links-source":"View source","repo-action-links-issue":"Report an issue","back-to-top":"Back to top","search-no-results-text":"No results","search-matching-documents-text":"matching documents","search-copy-link-title":"Copy link to search","search-hide-matches-text":"Hide additional matches","search-more-match-text":"more match in this document","search-more-matches-text":"more matches in this document","search-clear-button-title":"Clear","search-text-placeholder":"","search-detached-cancel-button-title":"Cancel","search-submit-button-title":"Submit","search-label":"Search","toggle-section":"Toggle section","toggle-sidebar":"Toggle sidebar navigation","toggle-dark-mode":"Toggle dark mode","toggle-reader-mode":"Toggle reader mode","toggle-navigation":"Toggle navigation","crossref-fig-title":"Figure","crossref-tbl-title":"Table","crossref-lst-title":"Listing","crossref-thm-title":"Theorem","crossref-lem-title":"Lemma","crossref-cor-title":"Corollary","crossref-prp-title":"Proposition","crossref-cnj-title":"Conjecture","crossref-def-title":"Definition","crossref-exm-title":"Example","crossref-exr-title":"Exercise","crossref-ch-prefix":"Chapter","crossref-apx-prefix":"Appendix","crossref-sec-prefix":"Section","crossref-eq-prefix":"Equation","crossref-lof-title":"List of Figures","crossref-lot-title":"List of Tables","crossref-lol-title":"List of Listings","environment-proof-title":"Proof","environment-remark-title":"Remark","environment-solution-title":"Solution","listing-page-order-by":"Order By","listing-page-order-by-default":"Default","listing-page-order-by-date-asc":"Oldest","listing-page-order-by-date-desc":"Newest","listing-page-order-by-number-desc":"High to Low","listing-page-order-by-number-asc":"Low to High","listing-page-field-date":"Date","listing-page-field-title":"Title","listing-page-field-description":"Description","listing-page-field-author":"Author","listing-page-field-filename":"File Name","listing-page-field-filemodified":"Modified","listing-page-field-subtitle":"Subtitle","listing-page-field-readingtime":"Reading Time","listing-page-field-wordcount":"Word Count","listing-page-field-categories":"Categories","listing-page-minutes-compact":"{0} min","listing-page-category-all":"All","listing-page-no-matches":"No matching items","listing-page-words":"{0} words","listing-page-filter":"Filter","draft":"Draft"},"metadata":{"lang":"../../../en","fig-responsive":true,"quarto-version":"1.8.26","theme":"cosmo"},"extensions":{"book":{"multiFile":true}}}},"projectFormats":["html"]}